README.md
setup.py
queueing_rnn/QRNN.py
queueing_rnn/__init__.py
queueing_rnn.egg-info/PKG-INFO
queueing_rnn.egg-info/SOURCES.txt
queueing_rnn.egg-info/dependency_links.txt
queueing_rnn.egg-info/top_level.txt