Metadata-Version: 2.1
Name: queueing-rnn
Version: 1.0.4
Summary: Queueing Recurrent Neural Network
Home-page: https://github.com/bilkosem/queueing_rnn
Author: bilkosem
Author-email: bilkos92@gmail.com
License: UNKNOWN
Platform: UNKNOWN
Classifier: Programming Language :: Python :: 3
Classifier: License :: OSI Approved :: MIT License
Classifier: Operating System :: OS Independent
